toolregistry/__init__.py
toolregistry/executor.py
toolregistry/parameter_models.py
toolregistry/py.typed
toolregistry/tool.py
toolregistry/tool_registry.py
toolregistry/tool_wrapper.py
toolregistry/utils.py
toolregistry/hub/__init__.py
toolregistry/langchain/__init__.py
toolregistry/langchain/integration.py
toolregistry/mcp/__init__.py
toolregistry/mcp/integration.py
toolregistry/mcp/utils.py
toolregistry/native/__init__.py
toolregistry/native/integration.py
toolregistry/native/utils.py
toolregistry/openapi/__init__.py
toolregistry/openapi/integration.py
toolregistry/openapi/utils.py
toolregistry/types/__init__.py
toolregistry/types/common.py
toolregistry/types/anthropic/__init__.py
toolregistry/types/gemini/__init__.py
toolregistry/types/openai/__init__.py
toolregistry/types/openai/chat_completion.py
toolregistry/types/openai/response.py
toolregistry-0.4.14.dist-info/licenses/LICENSE
toolregistry-0.4.14.dist-info/METADATA
toolregistry-0.4.14.dist-info/WHEEL
toolregistry-0.4.14.dist-info/top_level.txt
toolregistry-0.4.14.dist-info/RECORD
