Metadata-Version: 2.4
Name: toolregistry
Version: 0.4.14
Summary: ToolRegistry: a library for easier function calling and tool use in LLMs
Author-email: Oaklight <oaklight@gmx.com>
License-Expression: MIT
Project-URL: Documentation, https://toolregistry.lab.oaklight.cn
Project-URL: Repository, https://github.com/Oaklight/ToolRegistry
Project-URL: Issues, https://github.com/Oaklight/ToolRegistry/issues
Classifier: Intended Audience :: Developers
Classifier: Programming Language :: Python :: 3
Classifier: Topic :: Software Development :: Libraries :: Python Modules
Classifier: Topic :: Scientific/Engineering :: Artificial Intelligence
Requires-Python: >=3.8
License-File: LICENSE
Requires-Dist: pydantic<3.0.0,>=2.7.2
Requires-Dist: loguru>=0.7.3
Requires-Dist: dill>=0.4.0
Requires-Dist: httpx>=0.28.1
Requires-Dist: fake-useragent>=2.0.0
Requires-Dist: beautifulsoup4>=4.13.4
Provides-Extra: hub
Requires-Dist: toolregistry-hub>=0.4.14; extra == "hub"
Provides-Extra: mcp
Requires-Dist: fastmcp>=2.3.0; extra == "mcp"
Provides-Extra: openapi
Requires-Dist: PyYAML>=6.0.2; extra == "openapi"
Requires-Dist: jsonref>=1.1.0; extra == "openapi"
Provides-Extra: langchain
Requires-Dist: langchain-core<0.4,>=0.3; extra == "langchain"
Requires-Dist: langchain-community<0.4,>=0.3; extra == "langchain"
Provides-Extra: dev
Requires-Dist: python-dotenv>=1.0.1; extra == "dev"
Requires-Dist: openai>=1.79.0; extra == "dev"
Requires-Dist: fastapi>=0.115.12; extra == "dev"
Requires-Dist: pyright>=1.1.402; extra == "dev"
Requires-Dist: build>=1.2.2.post1; extra == "dev"
Requires-Dist: twine>=6.1.0; extra == "dev"
Requires-Dist: deprecated>=1.2.18; extra == "dev"
Provides-Extra: test
Requires-Dist: pytest>=7.0.0; extra == "test"
Requires-Dist: pytest-cov>=4.0.0; extra == "test"
Requires-Dist: pytest-asyncio>=0.21.0; extra == "test"
Requires-Dist: pytest-mock>=3.10.0; extra == "test"
Requires-Dist: coverage>=7.0.0; extra == "test"
Dynamic: license-file
